cmlbib/__init__.py
cmlbib/binaries.py
cmlbib/parser.py
cmlbib-0.1.2.dist-info/METADATA
cmlbib-0.1.2.dist-info/WHEEL
cmlbib-0.1.2.dist-info/entry_points.txt
cmlbib-0.1.2.dist-info/top_level.txt
cmlbib-0.1.2.dist-info/RECORD
