Metadata-Version: 2.1
Name: cmlbib
Version: 0.1.2
Summary: UNKNOWN
Home-page: UNKNOWN
Author: UNKNOWN
Author-email: UNKNOWN
License: UNKNOWN
Platform: UNKNOWN
Requires-Dist: Click (==8.*)
Requires-Dist: bibtexparser (==1.2.0)
Requires-Dist: tqdm (==4.*)
